odoo/addons/stock_vertical_lift_qty_by_packaging/README.rst
odoo/addons/stock_vertical_lift_qty_by_packaging/__init__.py
odoo/addons/stock_vertical_lift_qty_by_packaging/__manifest__.py
odoo/addons/stock_vertical_lift_qty_by_packaging/i18n/it.po
odoo/addons/stock_vertical_lift_qty_by_packaging/i18n/stock_vertical_lift_qty_by_packaging.pot
odoo/addons/stock_vertical_lift_qty_by_packaging/models/__init__.py
odoo/addons/stock_vertical_lift_qty_by_packaging/models/vertical_lift_operation_base.py
odoo/addons/stock_vertical_lift_qty_by_packaging/readme/CONTRIBUTORS.md
odoo/addons/stock_vertical_lift_qty_by_packaging/readme/DESCRIPTION.md
odoo/addons/stock_vertical_lift_qty_by_packaging/static/description/icon.png
odoo/addons/stock_vertical_lift_qty_by_packaging/static/description/index.html
odoo/addons/stock_vertical_lift_qty_by_packaging/views/vertical_lift_operation_base_views.xml
odoo_addon_stock_vertical_lift_qty_by_packaging-18.0.1.0.0.3.dist-info/METADATA
odoo_addon_stock_vertical_lift_qty_by_packaging-18.0.1.0.0.3.dist-info/WHEEL
odoo_addon_stock_vertical_lift_qty_by_packaging-18.0.1.0.0.3.dist-info/top_level.txt
odoo_addon_stock_vertical_lift_qty_by_packaging-18.0.1.0.0.3.dist-info/RECORD
